AUTHORS.rst
CONTRIBUTING.rst
HISTORY.rst
LICENSE
MANIFEST.in
README.rst
requirements.txt
setup.py
django_leads.egg-info/PKG-INFO
django_leads.egg-info/SOURCES.txt
django_leads.egg-info/dependency_links.txt
django_leads.egg-info/not-zip-safe
django_leads.egg-info/requires.txt
django_leads.egg-info/top_level.txt
leads/__init__.py
leads/__init__.pyc
leads/admin.py
leads/admin.pyc
leads/forms.py
leads/forms.pyc
leads/models.py
leads/models.pyc
leads/urls.py
leads/urls.pyc
leads/utils.py
leads/utils.pyc
leads/views.py
leads/views.pyc
leads/__pycache__/__init__.cpython-33.pyc
leads/__pycache__/admin.cpython-33.pyc
leads/__pycache__/forms.cpython-33.pyc
leads/__pycache__/models.cpython-33.pyc
leads/__pycache__/urls.cpython-33.pyc
leads/__pycache__/utils.cpython-33.pyc
leads/__pycache__/views.cpython-33.pyc
leads/locale/es/LC_MESSAGES/django.mo
leads/locale/es/LC_MESSAGES/django.po
leads/static/css/bootstrap-theme.css
leads/static/css/bootstrap-theme.min.css
leads/static/css/bootstrap.css
leads/static/css/bootstrap.min.css
leads/static/css/cover.css
leads/static/css/leads.css
leads/static/fonts/glyphicons-halflings-regular.eot
leads/static/fonts/glyphicons-halflings-regular.svg
leads/static/fonts/glyphicons-halflings-regular.ttf
leads/static/fonts/glyphicons-halflings-regular.woff
leads/static/img/.gitignore
leads/static/js/bootstrap.js
leads/static/js/bootstrap.min.js
leads/static/js/jquery.min.js
leads/static/js/leads.js
leads/templates/leads/base.html
leads/templates/leads/index.html
leads/templates/leads/thanks_register.html