Metadata-Version: 1.1
Name: django-leads
Version: 0.1.4
Summary: An easy, functional and customizable lead page for your next big thing, ready to use in your django project.
Home-page: https://github.com/dnmellen/django-leads
Author: Diego Navarro Mellén
Author-email: dnmellen@gmail.com
License: BSD
Keywords: django-leads
Platform: UNKNOWN
Classifier: Development Status :: 2 - Pre-Alpha
Classifier: Framework :: Django
Classifier: Intended Audience :: Developers
Classifier: License :: OSI Approved :: BSD License
Classifier: Natural Language :: English
Classifier: Programming Language :: Python :: 2
Classifier: Programming Language :: Python :: 2.6
Classifier: Programming Language :: Python :: 2.7
Classifier: Programming Language :: Python :: 3
Classifier: Programming Language :: Python :: 3.3
